design.sv
module PRPG(clk, clr, X_out);
input clk;
input clr;
output [3:1] X_out;
reg [3:1] tmp;
initial tmp = 3'b1;
always@ (posedge clk)
    begin
        if (clr)
            tmp<=1;
        else
        begin
            tmp<={tmp[3:1],tmp[3]^tmp[1]};
        end
    end
assign  X_out = tmp;
endmodule

testbench.sv
module PRPG_tb;
reg clk,clr;
wire [3:1] X_out;
initial begin
    #0;
    forever
    begin
        clk = 1'b0;
        #5 clk = 1'b1;
        #5;
    end
end
initial begin
    #0 clr=1'b1;  
    #10 clr=1'b0;
    #190 $finish;
end
PRPG PRPG_tb(.clk(clk), .clr(clr), .X_out(X_out));
initial begin
    $dumpfile("PRPG.vcd");
    $dumpvars(0, PRPG_tb);
end
endmodule

PRPG.vcd
$date
	Sun May 15 16:10:27 2022
$end
$version
	Icarus Verilog
$end
$timescale
	1s
$end
$scope module PRPG_tb $end
$scope module PRPG_tb $end
$var wire 3 ! X_out [3:1] $end
$var wire 1 " clk $end
$var wire 1 # clr $end
$var reg 3 $ tmp [3:1] $end
$upscope $end
$upscope $end
$enddefinitions $end
#0
$dumpvars
b1 $
1#
0"
b1 !
$end
#5
1"
#10
0"
0#
#15
b11 $
b11 !
1"
#20
0"
#25
b111 $
b111 !
1"
#30
0"
#35
b110 $
b110 !
1"
#40
0"
#45
b101 $
b101 !
1"
#50
0"
#55
b10 $
b10 !
1"
#60
0"
#65
b100 $
b100 !
1"
#70
0"
#75
b1 $
b1 !
1"
#80
0"
#85
b11 $
b11 !
1"
#90
0"
#95
b111 $
b111 !
1"
#100
0"
#105
b110 $
b110 !
1"
#110
0"
#115
b101 $
b101 !
1"
#120
0"
#125
b10 $
b10 !
1"
#130
0"
#135
b100 $
b100 !
1"
#140
0"
#145
b1 $
b1 !
1"
#150
0"
#155
b11 $
b11 !
1"
#160
0"
#165
b111 $
b111 !
1"
#170
0"
#175
b110 $
b110 !
1"
#180
0"
#185
b101 $
b101 !
1"
#190
0"
#195
b10 $
b10 !
1"
